core/__init__.py
core/__main__.py
core/cli.py
core/patterns.py
core/utils.py
cppast-1.0.0.dist-info/licenses/LICENSE
cppast-1.0.0.dist-info/METADATA
cppast-1.0.0.dist-info/WHEEL
cppast-1.0.0.dist-info/entry_points.txt
cppast-1.0.0.dist-info/top_level.txt
cppast-1.0.0.dist-info/RECORD
