Metadata-Version: 2.4
Name: cppast
Version: 1.0.0
Summary: C++ AST CLI tool with AST/graph visualization and pattern matching
Home-page: https://github.com/amanhas/cppast
Author: Abhishek Manhas
License: MIT
Classifier: Programming Language :: Python :: 3
Classifier: License :: OSI Approved :: MIT License
Classifier: Operating System :: OS Independent
Requires-Python: >=3.7
License-File: LICENSE
Requires-Dist: clang
Requires-Dist: graphviz
Requires-Dist: networkx
Requires-Dist: typer[all]
Dynamic: author
Dynamic: classifier
Dynamic: description
Dynamic: description-content-type
Dynamic: home-page
Dynamic: license
Dynamic: license-file
Dynamic: requires-dist
Dynamic: requires-python
Dynamic: summary
